jq_utils/__init__.py
jq_utils-0.1.1.dist-info/METADATA
jq_utils-0.1.1.dist-info/WHEEL
jq_utils-0.1.1.dist-info/top_level.txt
jq_utils-0.1.1.dist-info/RECORD
