Metadata-Version: 2.4
Name: jq-utils
Version: 0.1.1
Summary: JQ-style dictionary and list access for Python
Author-email: dotlabs <teams@dotlabs.dev>
License: MIT
Project-URL: Homepage, https://github.com/dotlabshq/jq-utils
Project-URL: Repository, https://github.com/dotlabshq/jq-utils.git
Project-URL: Bug Tracker, https://github.com/dotlabshq/jq-utils/issues
Requires-Python: >=3.7
Provides-Extra: test
Requires-Dist: pytest>=7.0.0; extra == "test"
